netron/__init__.py
netron/acuity-metadata.json
netron/acuity.js
netron/armnn-metadata.json
netron/armnn-schema.js
netron/armnn.js
netron/barracuda.js
netron/base.js
netron/bigdl-metadata.json
netron/bigdl-proto.js
netron/bigdl.js
netron/browser.js
netron/caffe-metadata.json
netron/caffe-proto.js
netron/caffe.js
netron/caffe2-metadata.json
netron/caffe2-proto.js
netron/caffe2.js
netron/catboost.js
netron/circle-metadata.json
netron/circle-schema.js
netron/circle.js
netron/cntk-metadata.json
netron/cntk-proto.js
netron/cntk.js
netron/coreml-metadata.json
netron/coreml-proto.js
netron/coreml.js
netron/dagre.js
netron/darknet-metadata.json
netron/darknet.js
netron/dl4j-metadata.json
netron/dl4j.js
netron/dlc-metadata.json
netron/dlc-schema.js
netron/dlc.js
netron/dnn-metadata.json
netron/dnn-proto.js
netron/dnn.js
netron/dot.js
netron/espresso-metadata.json
netron/espresso.js
netron/executorch-schema.js
netron/executorch.js
netron/favicon.ico
netron/flatbuffers.js
netron/flax.js
netron/flexbuffers.js
netron/flux-metadata.json
netron/flux.js
netron/gguf.js
netron/grapher.css
netron/grapher.js
netron/hailo-metadata.json
netron/hailo.js
netron/hdf5.js
netron/hickle.js
netron/icon.png
netron/imgdnn.js
netron/index.html
netron/index.js
netron/json.js
netron/kann-metadata.json
netron/kann-schema.js
netron/kann.js
netron/keras-metadata.json
netron/keras-proto.js
netron/keras.js
netron/kmodel.js
netron/lasagne-metadata.json
netron/lasagne.js
netron/lightgbm.js
netron/mediapipe.js
netron/megengine-metadata.json
netron/megengine-schema.js
netron/megengine.js
netron/message.js
netron/mlir-metadata.json
netron/mlir.js
netron/mlnet-metadata.json
netron/mlnet.js
netron/mnn-metadata.json
netron/mnn-schema.js
netron/mnn.js
netron/mslite-metadata.json
netron/mslite-schema.js
netron/mslite.js
netron/mxnet-metadata.json
netron/mxnet.js
netron/ncnn-metadata.json
netron/ncnn.js
netron/nnabla-metadata.json
netron/nnabla-proto.js
netron/nnabla.js
netron/nnc.js
netron/nnef.js
netron/node.js
netron-8.8.8.dist-info/METADATA
netron-8.8.8.dist-info/WHEEL
netron-8.8.8.dist-info/entry_points.txt
netron-8.8.8.dist-info/top_level.txt
netron-8.8.8.dist-info/RECORD
