Metadata-Version: 2.4
Name: netron
Version: 8.8.8
Summary: Viewer for neural network, deep learning and machine learning models.
Author-email: Lutz Roeder <lutzroeder@users.noreply.github.com>
License: MIT
Project-URL: homepage, https://github.com/lutzroeder/netron
Keywords: onnx,keras,tensorflow,tflite,coreml,mxnet,caffe,caffe2,torchscript,pytorch,ncnn,mnn,openvino,darknet,paddlepaddle,chainer,artificial intelligence,machine learning,deep learning,neural network,visualizer,viewer
Classifier: Intended Audience :: Developers
Classifier: Intended Audience :: Education
Classifier: Intended Audience :: Science/Research
Classifier: Programming Language :: Python :: 3
Classifier: Programming Language :: Python :: 3.6
Classifier: Topic :: Software Development
Classifier: Topic :: Software Development :: Libraries
Classifier: Topic :: Software Development :: Libraries :: Python Modules
Classifier: Topic :: Scientific/Engineering
Classifier: Topic :: Scientific/Engineering :: Mathematics
Classifier: Topic :: Scientific/Engineering :: Artificial Intelligence
Classifier: Topic :: Scientific/Engineering :: Visualization
